pywavez/Controller.py
pywavez/ControllerNode.py
pywavez/NodeUpdate.py
pywavez/ReceivedCommand.py
pywavez/RemoteSerialDevice.py
pywavez/SerialDevice.py
pywavez/SerialDeviceBase.py
pywavez/SerialProtocol.py
pywavez/Transmission.py
pywavez/__init__.py
pywavez/__version__.py
pywavez/util.py
pywavez-0.1.0.dist-info/LICENSE
pywavez-0.1.0.dist-info/METADATA
pywavez-0.1.0.dist-info/WHEEL
pywavez-0.1.0.dist-info/entry_points.txt
pywavez-0.1.0.dist-info/top_level.txt
pywavez-0.1.0.dist-info/RECORD
