Metadata-Version: 2.1
Name: pywavez
Version: 0.1.0
Summary: Native Python implementation of the ZWave protocol
Home-page: https://github.com/spacedentist/pywavez
Author: Sven Over
Author-email: sp@cedenti.st
License: MIT
Download-URL: https://github.com/spacedentist/pywavez/archive/0.1.0.tar.gz
Platform: UNKNOWN
Requires-Dist: asyncinit
Requires-Dist: pyserial
Requires-Dist: pyserial-asyncio
